{"format":"CHIP-0007","name":"tiwa-london","description":"If she says she's in London and you see her, you're in London too.","minting_tool":"TeamBevel","sensitive_content":false,"series_number":18,"series_total":420,"collection":{"name":"Zuri NFT Tickets for Free Lunch","id":"b774f676-c1d5-422e-beed-00ef5510c64d","attributes":[{"type":"description","value":"Rewards for accomplishments during HNGi9."}]},"gender":"","uuid":"78da7aeb-8352-4e25-89ac-dc48b5984089","hash":"B9CAD7B34CB93D492D25BF876961EE567174A6F70956D59774329390F649ECFB"}